cicada/__init__.py
cicada/coding/__init__.py
cicada/coding/code_cache.py
cicada/coding/code_executor.py
cicada/coding/code_generator.py
cicada/coding/coder.py
cicada/core/__init__.py
cicada/core/basics.py
cicada/core/embeddings.py
cicada/core/model.py
cicada/core/rerank.py
cicada/core/types.py
cicada/core/utils.py
cicada/describe/__init__.py
cicada/describe/describer_v2.py
cicada/describe/utils.py
cicada/describe/deprecated/assistant.py
cicada/describe/deprecated/describer.py
cicada/feedback/__init__.py
cicada/feedback/feedback_judge.py
cicada/feedback/visual_feedback.py
cicada/feedback/visual_qa.py
cicada/geometry_pipeline/__init__.py
cicada/geometry_pipeline/angles.py
cicada/geometry_pipeline/convert.py
cicada/geometry_pipeline/snapshots.py
cicada/retrieval/__init__.py
cicada/retrieval/basics.py
cicada/retrieval/pgvector_store.py
cicada/retrieval/sqlitevec_store.py
cicada/retrieval/deprecated/extract_from_py_module.py
cicada/retrieval/deprecated/init_vdb.py
cicada/tools/__init__.py
cicada/tools/build123d_retriever.py
cicada/tools/code_dochelper.py
cicada/tools/web_reader.py
cicada/workflow/__init__.py
cicada/workflow/codecad_agent.py
cicada_agent-0.7.4.dist-info/licenses/LICENSE
cicada_agent-0.7.4.dist-info/METADATA
cicada_agent-0.7.4.dist-info/WHEEL
cicada_agent-0.7.4.dist-info/top_level.txt
cicada_agent-0.7.4.dist-info/RECORD
