Metadata-Version: 2.4
Name: cicada-agent
Version: 0.7.4
Summary: A Python package for the Cicada project
Author-email: Oaklight <oaklight@gmx.com>
License: MIT License
Classifier: Programming Language :: Python :: 3
Classifier: Operating System :: OS Independent
Requires-Python: >=3.10
License-File: LICENSE
Requires-Dist: openai>=1.6.8
Requires-Dist: pydantic>=2.10.6
Requires-Dist: httpx>=0.28.1
Requires-Dist: pyyaml>=6.0.2
Requires-Dist: blessed>=1.20.0
Requires-Dist: pillow>=11.1.0
Requires-Dist: toolregistry>=0.2.0
Requires-Dist: sqlite-vec>=0.1.6
Requires-Dist: pgvector>=0.4.0
Requires-Dist: sqlalchemy>=2.0.36
Requires-Dist: psycopg>=3.2.6
Requires-Dist: psycopg_binary>=3.2.6
Requires-Dist: questionary==2.1.0
Provides-Extra: codecad
Requires-Dist: gmsh>=4.13.1; extra == "codecad"
Requires-Dist: plyfile==1.1; extra == "codecad"
Requires-Dist: trimesh==4.5.1; extra == "codecad"
Requires-Dist: pyglet<2; extra == "codecad"
Requires-Dist: pyrender==0.1.45; extra == "codecad"
Requires-Dist: build123d==0.8.0; extra == "codecad"
Provides-Extra: all
Requires-Dist: openai>=1.6.8; extra == "all"
Requires-Dist: pydantic>=2.10.6; extra == "all"
Requires-Dist: httpx>=0.28.1; extra == "all"
Requires-Dist: pyyaml>=6.0.2; extra == "all"
Requires-Dist: blessed>=1.20.0; extra == "all"
Requires-Dist: pillow>=11.1.0; extra == "all"
Requires-Dist: toolregistry>=0.2.0; extra == "all"
Requires-Dist: sqlite-vec>=0.1.6; extra == "all"
Requires-Dist: pgvector>=0.4.0; extra == "all"
Requires-Dist: sqlalchemy>=2.0.36; extra == "all"
Requires-Dist: questionary==2.1.0; extra == "all"
Requires-Dist: gmsh>=4.13.1; extra == "all"
Requires-Dist: plyfile==1.1; extra == "all"
Requires-Dist: trimesh==4.5.1; extra == "all"
Requires-Dist: pyglet<2; extra == "all"
Requires-Dist: pyrender==0.1.45; extra == "all"
Requires-Dist: build123d==0.8.0; extra == "all"
Dynamic: license-file
